aisploit/__init__.py
aisploit/classifiers/__init__.py
aisploit/classifiers/amazon/__init__.py
aisploit/classifiers/amazon/comprehend.py
aisploit/classifiers/huggingface/__init__.py
aisploit/classifiers/huggingface/bert_score.py
aisploit/classifiers/huggingface/bleu.py
aisploit/classifiers/huggingface/pipeline_prompt_injection.py
aisploit/classifiers/markdown.py
aisploit/classifiers/openai/__init__.py
aisploit/classifiers/openai/moderation.py
aisploit/classifiers/package_hallucination.py
aisploit/classifiers/presidio/__init__.py
aisploit/classifiers/presidio/presidio_analyser.py
aisploit/classifiers/repeated_token.py
aisploit/classifiers/self_similarity.py
aisploit/classifiers/text.py
aisploit/converters/__init__.py
aisploit/converters/base64.py
aisploit/converters/case.py
aisploit/converters/gender.py
aisploit/converters/join.py
aisploit/converters/keyboard_typo.py
aisploit/converters/no_op.py
aisploit/converters/remove_punctuation.py
aisploit/converters/sequence.py
aisploit/converters/stemming.py
aisploit/converters/translation.py
aisploit/converters/unicode_confusable.py
aisploit/converters/unicode_tags.py
aisploit/core/__init__.py
aisploit/core/callbacks.py
aisploit/core/classifier.py
aisploit/core/converter.py
aisploit/core/dataset.py
aisploit/core/generator.py
aisploit/core/job.py
aisploit/core/model.py
aisploit/core/prompt.py
aisploit/core/report.py
aisploit/core/target.py
aisploit/core/vectorstore.py
aisploit/datasets/__init__.py
aisploit/datasets/programming_questions/data.csv
aisploit/datasets/prompt.py
aisploit/datasets/prompts/aim.yaml
aisploit/datasets/prompts/developer_mode_2.yaml
aisploit/datasets/prompts/evil_confidant.yaml
aisploit/datasets/prompts/steve.yaml
aisploit/datasets/prompts/ucar.yaml
aisploit/datasets/sample.py
aisploit/demo/__init__.py
aisploit/demo/gandalf.py
aisploit/demo/rag.py
aisploit/embeddings/__init__.py
aisploit/embeddings/bedrock.py
aisploit/embeddings/google.py
aisploit/embeddings/huggingface.py
aisploit/embeddings/ollama.py
aisploit-0.0.25.dist-info/LICENSE
aisploit-0.0.25.dist-info/METADATA
aisploit-0.0.25.dist-info/WHEEL
aisploit-0.0.25.dist-info/RECORD
