Metadata-Version: 2.1
Name: aisploit
Version: 0.0.25
Summary: Tiny package designed to support red teams and penetration testers in exploiting large language model AI solutions.
Home-page: https://github.com/hupe1980/aisploit
License: MIT
Keywords: security,ai,pentest,red-team,responsible-ai,red-team-tools,llm,generative-ai,ai-red-team,langchain
Author: hupe1980
Requires-Python: >=3.12,<4.0
Classifier: License :: OSI Approved :: MIT License
Classifier: Programming Language :: Python
Classifier: Programming Language :: Python :: 3
Classifier: Programming Language :: Python :: 3.12
Classifier: Topic :: Scientific/Engineering :: Artificial Intelligence
Classifier: Topic :: Security
Requires-Dist: bert-score (>=0.3.13,<0.4.0)
Requires-Dist: boto3 (>=1.34.88,<2.0.0)
Requires-Dist: brotli (>=1.1.0,<2.0.0)
Requires-Dist: confusables (>=1.2.0,<2.0.0)
Requires-Dist: evaluate (>=0.4.1,<0.5.0)
Requires-Dist: imapclient (>=3.0.1,<4.0.0)
Requires-Dist: jinja2 (>=3.1.3,<4.0.0)
Requires-Dist: langchain-anthropic (>=0.1.6,<0.2.0)
Requires-Dist: langchain-community (>=0.0.24)
Requires-Dist: langchain-core (>=0.1.26)
Requires-Dist: langchain-google-genai (>=1.0.1,<2.0.0)
Requires-Dist: langchain-openai (>=0.1.1)
Requires-Dist: nltk (>=3.8.1,<4.0.0)
Requires-Dist: numpy (>=1.26.4,<2.0.0)
Requires-Dist: opencv-python (>=4.9.0.80,<5.0.0.0)
Requires-Dist: pillow (>=10.3.0,<11.0.0)
Requires-Dist: presidio-analyzer (>=2.2.354,<3.0.0)
Requires-Dist: pydantic (>=2.6.2,<3.0.0)
Requires-Dist: python-docx (>=1.1.0,<2.0.0)
Requires-Dist: python-dotenv (>=1.0.1,<2.0.0)
Requires-Dist: requests (>=2.31.0,<3.0.0)
Requires-Dist: sentence-transformers (>=2.7.0,<3.0.0)
Requires-Dist: stdlib-list (>=0.10.0,<0.11.0)
Requires-Dist: torch (>=2.2.2,<3.0.0)
Requires-Dist: tqdm (>=4.66.2,<5.0.0)
Requires-Dist: transformers (>=4.38.1,<5.0.0)
Project-URL: Repository, https://github.com/hupe1980/aisploit
